{
    "2026-01-07": [
        {
            "kind": "CL",
            "n": 0,
            "title": "Welcome to COMP110!",
            "date": "2026-01-07",
            "deadline": "2026-01-07",
            "links": {
                "Slides": "/static/slides/cl00.pdf"
            }
        },
        {
            "kind": "LS",
            "n": 0,
            "title": "Syllabus Familiarity (Due Thursday 1/8)",
            "date": "2026-01-07",
            "deadline": "2026-01-08",
            "links": {
                "1. Read the Syllabus": "/resources/syllabus.html",
                "2. Complete Lesson 00 Responses on Gradescope": "https://www.gradescope.com/"
            }
        }
    ],
    "2026-01-08": [],
    "2026-01-09": [
        {
            "kind": "CL",
            "n": 1,
            "title": "Objects and Data Types",
            "date": "2026-01-09",
            "deadline": "2026-01-09",
            "links": {
                "Slides": "/static/slides/cl01.pdf",
                "Optional Reading": "/lessons/objects-data-types.html"
            }
        },
        {
            "kind": "LS",
            "n": 1,
            "title": "Software Setup",
            "date": "2026-01-09",
            "deadline": "2026-01-09",
            "links": {
                "1. OS Update": "/resources/setup/os-update.html",
                "2. Docker, git, VS Code": "/resources/setup/software.html",
                "3. COMP110 Workspace": "/resources/setup/workspace.html",
                "4. Complete the LS01 Responses on Gradescope": "https://www.gradescope.com/"
            }
        },
        {
            "kind": "LS",
            "n": 2,
            "title": "Objects and Data Types",
            "date": "2026-01-09",
            "deadline": "2026-01-09",
            "links": {
                "Complete Lesson 02 Responses on Gradescope": "https://www.gradescope.com/"
            }
        },
        {
            "kind": "EX",
            "n": 0,
            "title": "Hello, World! (Due Thursday 1/15)",
            "date": "2026-01-09",
            "deadline": "2026-01-15",
            "links": {
                "": "/exercises/ex00_hello_world.html"
            }
        }
    ],
    "2026-01-10": [],
    "2026-01-11": []
}